py_agata/__init__.py
py_agata/py_agata.py
py_agata/error/__init__.py
py_agata/error/tests/__init__.py
py_agata/error/tests/test_clarke.py
py_agata/error/tests/test_cod.py
py_agata/error/tests/test_g_rmse.py
py_agata/error/tests/test_mard.py
py_agata/error/tests/test_rmse.py
py_agata/error/tests/test_time_delay.py
py_agata/glycemic_transformation/__init__.py
py_agata/glycemic_transformation/tests/__init__.py
py_agata/glycemic_transformation/tests/test_grade_eu_score.py
py_agata/glycemic_transformation/tests/test_grade_hyper_score.py
py_agata/glycemic_transformation/tests/test_grade_hypo_score.py
py_agata/glycemic_transformation/tests/test_grade_score.py
py_agata/glycemic_transformation/tests/test_hyper_index.py
py_agata/glycemic_transformation/tests/test_hypo_index.py
py_agata/glycemic_transformation/tests/test_igc.py
py_agata/glycemic_transformation/tests/test_mr_index.py
py_agata/input_validator/__init__.py
py_agata/input_validator/tests/__init__.py
py_agata/input_validator/tests/test_check_comparable_data.py
py_agata/input_validator/tests/test_check_data_columns.py
py_agata/input_validator/tests/test_check_dataframe.py
py_agata/input_validator/tests/test_check_datetime_parameter.py
py_agata/input_validator/tests/test_check_float_parameter.py
py_agata/input_validator/tests/test_check_homogeneous_timegrid.py
py_agata/input_validator/tests/test_check_int_parameter.py
py_agata/input_validator/tests/test_check_ndarray_datetime_parameter.py
py_agata/input_validator/tests/test_check_ndarray_float_parameter.py
py_agata/input_validator/tests/test_check_same_length_dataframe.py
py_agata/input_validator/tests/test_check_same_length_ndarray.py
py_agata/input_validator/tests/test_check_str_parameter.py
py_agata/inspection/__init__.py
py_agata/inspection/tests/__init__.py
py_agata/inspection/tests/test_find_extended_hypoglycemic_events.py
py_agata/inspection/tests/test_find_hyperglycemic_events.py
py_agata/inspection/tests/test_find_hyperglycemic_events_by_level.py
py_agata-0.0.8.dist-info/COPYING.md
py_agata-0.0.8.dist-info/METADATA
py_agata-0.0.8.dist-info/WHEEL
py_agata-0.0.8.dist-info/top_level.txt
py_agata-0.0.8.dist-info/RECORD
