Metadata-Version: 2.1
Name: py_agata
Version: 0.0.8
Summary: AGATA (Automated Glucose dATa Analysis): a toolbox to analyse glucose data.
Author-email: Giacomo Cappon <cappongiacomo@gmail.com>
Project-URL: Homepage, https://github.com/gcappon/py_agata
Project-URL: Bug Tracker, https://github.com/gcappon/py_agata/issues
Classifier: Programming Language :: Python :: 3
Classifier: License :: OSI Approved :: GNU General Public License v3 (GPLv3)
Classifier: Operating System :: OS Independent
Classifier: Intended Audience :: Science/Research
Classifier: Topic :: Scientific/Engineering
Requires-Python: >=3.9
License-File: COPYING.md
Requires-Dist: numpy
Requires-Dist: pandas
Requires-Dist: scipy
Requires-Dist: pytest
Requires-Dist: pytest-cov
Requires-Dist: openpyxl
Requires-Dist: statsmodels
